justpipe/__init__.py
justpipe/graph.py
justpipe/handlers.py
justpipe/invoker.py
justpipe/middleware.py
justpipe/pipe.py
justpipe/py.typed
justpipe/registry.py
justpipe/runner.py
justpipe/steps.py
justpipe/types.py
justpipe/utils.py
justpipe/visualization/__init__.py
justpipe/visualization/ast.py
justpipe/visualization/builder.py
justpipe/visualization/mermaid.py
justpipe-0.5.4.dist-info/METADATA
justpipe-0.5.4.dist-info/WHEEL
justpipe-0.5.4.dist-info/licenses/LICENSE
justpipe-0.5.4.dist-info/RECORD
