Metadata-Version: 2.4
Name: justpipe
Version: 0.5.4
Summary: Your code is the graph. Async, streaming pipelines for AI.
Project-URL: Homepage, https://github.com/plar/justpipe
Project-URL: Repository, https://github.com/plar/justpipe
Project-URL: Issues, https://github.com/plar/justpipe/issues
Author-email: Pavel Larkin <laxkin@gmail.com>
License-File: LICENSE
Keywords: ai,async,dag,llm,orchestration,pipeline,streaming
Classifier: Development Status :: 4 - Beta
Classifier: Intended Audience :: Developers
Classifier: License :: OSI Approved :: MIT License
Classifier: Programming Language :: Python :: 3.12
Classifier: Topic :: Software Development :: Libraries :: Python Modules
Classifier: Typing :: Typed
Requires-Python: >=3.12
Provides-Extra: examples
Requires-Dist: google-genai>=0.3.0; extra == 'examples'
Requires-Dist: openai>=1.0.0; extra == 'examples'
Requires-Dist: rich>=13.0.0; extra == 'examples'
Provides-Extra: retry
Requires-Dist: tenacity>=9.1.2; extra == 'retry'
